Metadata-Version: 1.1
Name: python-cern-sso-krb
Version: 1.3.3
Summary: Cern Single-Single-Sign-On driver
Home-page: https://github.com/cerndb/cern-sso-python
Author: Albin Stjerna
Author-email: albin.stjerna@cern.ch
License: GPLv3
Keywords: authentication sso cern kerberos
Platform: UNKNOWN
Classifier: Development Status :: 4 - Beta
Classifier: Intended Audience :: Developers
Classifier: License :: OSI Approved :: GNU General Public License v3 (GPLv3)
Classifier: Programming Language :: Python :: 2.6
Classifier: Programming Language :: Python :: 2.7
Classifier: Programming Language :: Python :: 3
